BlynkLib.py
README.md
setup.cfg
setup.py
blynk_library_python.egg-info/PKG-INFO
blynk_library_python.egg-info/SOURCES.txt
blynk_library_python.egg-info/dependency_links.txt
blynk_library_python.egg-info/top_level.txt