Metadata-Version: 1.1
Name: blynk-library-python
Version: 0.2.0
Summary: Blynk library
Home-page: http://www.blynk.cc
Author: Volodymyr Shymanskyy
Author-email: vshymanskyi@gmail.com
License: MIT
Platform: any
Classifier: Topic :: Software Development :: Libraries :: Python Modules
Classifier: Development Status :: 4 - Beta
Classifier: License :: OSI Approved :: MIT License
Classifier: Operating System :: POSIX :: Linux
Classifier: Operating System :: Microsoft :: Windows
Classifier: Operating System :: MacOS :: MacOS X
